<!DOCTYPE tiles-definitions PUBLIC
        "-//Apache Software Foundation//DTD Tiles Configuration2.1//EN"
        "http://tiles.apache.org/dtds/tiles-config_2_1.dtd">
<tiles-definitions>

    <definition name="template-base" template="/WEB-INF/view/layouts/main.jsp">
        <put-attribute name="header" value="/WEB-INF/view/tiles/header.jsp"/>
        <put-attribute name="footer" value="/WEB-INF/view/tiles/footer.jsp"/>
    </definition>

    <definition name="list-topic" extends="template-base">
        <put-attribute name="title" value="Forum"/>
        <put-attribute name="content" value="/WEB-INF/view/forum/list-topic.jsp"/>
    </definition>

    <definition name="add-topic" extends="template-base">
        <put-attribute name="title" value="Add topic"/>
        <put-attribute name="content" value="/WEB-INF/view/forum/add-topic.jsp"/>
    </definition>


    <definition name="list-category" extends="template-base">
        <put-attribute name="title" value="Forum"/>
        <put-attribute name="content" value="/WEB-INF/view/forum/list-category.jsp"/>
    </definition>

    <definition name="user-registration-form" extends="template-base">
        <put-attribute name="title" value="Sign up"/>
        <put-attribute name="content" value="/WEB-INF/view/user/form-registration.jsp"/>
    </definition>

    <definition name="user-auth-form" extends="template-base">
        <put-attribute name="title" value="Sign up"/>
        <put-attribute name="content" value="/WEB-INF/view/user/form-auth.jsp"/>
    </definition>

</tiles-definitions>